simple_math_ss/__init__.py
simple_math_ss/core.py
simple_math_ss-0.1.0.dist-info/METADATA
simple_math_ss-0.1.0.dist-info/WHEEL
simple_math_ss-0.1.0.dist-info/top_level.txt
simple_math_ss-0.1.0.dist-info/RECORD
