Metadata-Version: 2.2
Name: simple-math-ss
Version: 0.1.0
Summary: A simple Python package to add one to a given number
Author: Savio
Author-email: saviosebastiankann@gmail.com
Classifier: Programming Language :: Python :: 3
Classifier: License :: OSI Approved :: MIT License
Classifier: Operating System :: OS Independent
Requires-Python: >=3.6
Dynamic: author
Dynamic: author-email
Dynamic: classifier
Dynamic: description
Dynamic: description-content-type
Dynamic: requires-python
Dynamic: summary
